comfy_mcp_server/__init__.py
comfy_mcp_server/api.py
comfy_mcp_server/compat.py
comfy_mcp_server/layout.py
comfy_mcp_server/models.py
comfy_mcp_server/settings.py
comfy_mcp_server/tools/__init__.py
comfy_mcp_server/tools/discovery.py
comfy_mcp_server/tools/execution.py
comfy_mcp_server/tools/system.py
comfy_mcp_server/tools/workflow.py
comfyui_easy_mcp-0.2.1.dist-info/METADATA
comfyui_easy_mcp-0.2.1.dist-info/WHEEL
comfyui_easy_mcp-0.2.1.dist-info/entry_points.txt
comfyui_easy_mcp-0.2.1.dist-info/licenses/LICENSE
comfyui_easy_mcp-0.2.1.dist-info/RECORD
