Metadata-Version: 2.4
Name: comfyui-easy-mcp
Version: 0.2.1
Summary: MCP server for ComfyUI workflow automation by IO-AtelierTech
Project-URL: Homepage, https://github.com/IO-AtelierTech/comfyui-mcp
Project-URL: Repository, https://github.com/IO-AtelierTech/comfyui-mcp
Project-URL: Documentation, https://github.com/IO-AtelierTech/comfyui-mcp/blob/main/README.md
Project-URL: Issues, https://github.com/IO-AtelierTech/comfyui-mcp/issues
Author-email: Danyiel Colin <danyiel5978@gmail.com>
Maintainer-email: IO-AtelierTech <ioateliertech@gmail.com>
License-Expression: MIT
License-File: LICENSE
Keywords: ai,claude,comfyui,image-generation,io-ateliertech,mcp,workflow
Classifier: Development Status :: 4 - Beta
Classifier: Intended Audience :: Developers
Classifier: License :: OSI Approved :: MIT License
Classifier: Programming Language :: Python :: 3
Classifier: Programming Language :: Python :: 3.10
Classifier: Programming Language :: Python :: 3.11
Classifier: Programming Language :: Python :: 3.12
Classifier: Topic :: Scientific/Engineering :: Artificial Intelligence
Requires-Python: >=3.10
Requires-Dist: coolname>=2.0.0
Requires-Dist: mcp[cli]>=1.2.1
Requires-Dist: networkx>=3.0
Requires-Dist: pydantic-settings>=2.0.0
Requires-Dist: pydantic>=2.0.0
Provides-Extra: dev
Requires-Dist: inline-snapshot>=0.10.0; extra == 'dev'
Requires-Dist: pytest-anyio>=0.0.0; extra == 'dev'
Requires-Dist: pytest-asyncio>=0.21.0; extra == 'dev'
Requires-Dist: pytest>=7.0.0; extra == 'dev'
